XlDemerge/__init__.py
XlDemerge/main.py
XlDemerge-0.1.0.dist-info/METADATA
XlDemerge-0.1.0.dist-info/WHEEL
XlDemerge-0.1.0.dist-info/top_level.txt
XlDemerge-0.1.0.dist-info/RECORD
