Metadata-Version: 2.1
Name: XlDemerge
Version: 0.1.0
Requires-Dist: openpyxl ==3.1.2
Requires-Dist: pandas ==1.5.3
Requires-Dist: numpy ==1.23.5
